margparse/__init__.py
margparse/_common.py
margparse/actions/__init__.py
margparse/actions/other.py
margparse/types/__init__.py
margparse/types/other.py
more_argparse-1.0.0.1.dist-info/LICENSE
more_argparse-1.0.0.1.dist-info/METADATA
more_argparse-1.0.0.1.dist-info/WHEEL
more_argparse-1.0.0.1.dist-info/top_level.txt
more_argparse-1.0.0.1.dist-info/RECORD
