Metadata-Version: 2.1
Name: more-argparse
Version: 1.0.0.1
Summary: Extra types and actions for argparse
Home-page: https://github.com/gaming32/more-argparse
Author: Gaming32
Author-email: gaming32i64@gmail.com
License: License :: OSI Approved :: MIT License
Platform: UNKNOWN
